universum/__init__.py
universum/__main__.py
universum/api.py
universum/config_creator.py
universum/configuration_support.py
universum/github_handler.py
universum/main.py
universum/nonci.py
universum/poll.py
universum/submit.py
universum/analyzers/__init__.py
universum/analyzers/pylint.py
universum/analyzers/svace.py
universum/analyzers/uncrustify.py
universum/analyzers/utils.py
universum/lib/__init__.py
universum/lib/ci_exception.py
universum/lib/gravity.py
universum/lib/module_arguments.py
universum/lib/utils.py
universum/modules/__init__.py
universum/modules/api_support.py
universum/modules/artifact_collector.py
universum/modules/code_report_collector.py
universum/modules/error_state.py
universum/modules/launcher.py
universum/modules/project_directory.py
universum/modules/reporter.py
universum/modules/structure_handler.py
universum/modules/automation_server/__init__.py
universum/modules/automation_server/automation_server.py
universum/modules/automation_server/base_server.py
universum/modules/automation_server/jenkins_server.py
universum/modules/automation_server/local_server.py
universum/modules/automation_server/teamcity_server.py
universum/modules/output/__init__.py
universum/modules/output/base_output.py
universum/modules/output/output.py
universum/modules/output/teamcity_output.py
universum/modules/output/terminal_based_output.py
universum/modules/vcs/__init__.py
universum/modules/vcs/base_vcs.py
universum/modules/vcs/gerrit_vcs.py
universum/modules/vcs/git_vcs.py
universum/modules/vcs/github_vcs.py
universum/modules/vcs/local_vcs.py
universum/modules/vcs/perforce_vcs.py
universum/modules/vcs/swarm.py
universum/modules/vcs/vcs.py
Universum-0.19.3.dist-info/LICENSE
Universum-0.19.3.dist-info/METADATA
Universum-0.19.3.dist-info/WHEEL
Universum-0.19.3.dist-info/top_level.txt
Universum-0.19.3.dist-info/RECORD
