Metadata-Version: 2.1
Name: Universum
Version: 0.19.3
Summary: Unifier of Continuous Integration
Home-page: UNKNOWN
Author: Ivan Keliukh <i.keliukh@samsung.com>, Kateryna Dovgan <k.dovgan@samsung.com>
License: BSD
Platform: UNKNOWN
Requires-Python: >=3.6
Requires-Dist: glob2
Requires-Dist: lxml
Requires-Dist: requests
Requires-Dist: sh
Requires-Dist: typing-extensions
Provides-Extra: docs
Requires-Dist: sphinx ; extra == 'docs'
Requires-Dist: sphinx-argparse ; extra == 'docs'
Requires-Dist: sphinx-rtd-theme ; extra == 'docs'
Provides-Extra: git
Requires-Dist: gitpython (>=3.0.5) ; extra == 'git'
Provides-Extra: github
Requires-Dist: cryptography ; extra == 'github'
Requires-Dist: gitpython (>=3.0.5) ; extra == 'github'
Requires-Dist: pygithub ; extra == 'github'
Provides-Extra: p4
Requires-Dist: p4python (>=2019.1) ; extra == 'p4'
Requires-Dist: pip (>=19) ; extra == 'p4'
Provides-Extra: test
Requires-Dist: coverage ; extra == 'test'
Requires-Dist: cryptography ; extra == 'test'
Requires-Dist: docker ; extra == 'test'
Requires-Dist: gitpython (>=3.0.5) ; extra == 'test'
Requires-Dist: httpretty ; extra == 'test'
Requires-Dist: mock ; extra == 'test'
Requires-Dist: mypy ; extra == 'test'
Requires-Dist: p4python (>=2019.1) ; extra == 'test'
Requires-Dist: pip (>=19) ; extra == 'test'
Requires-Dist: pygithub ; extra == 'test'
Requires-Dist: pylint ; extra == 'test'
Requires-Dist: pytest ; extra == 'test'
Requires-Dist: pytest-cov ; extra == 'test'
Requires-Dist: pytest-pylint ; extra == 'test'
Requires-Dist: sphinx ; extra == 'test'
Requires-Dist: sphinx-argparse ; extra == 'test'
Requires-Dist: sphinx-rtd-theme ; extra == 'test'
Requires-Dist: teamcity-messages ; extra == 'test'
